verseql/__init__.py
verseql/_expression.py
verseql/_order.py
verseql/_parser_listener.py
verseql/_projection.py
verseql/_query.py
verseql/_verseql.py
verseql/py.typed
verseql/generated/VerseQLLexer.py
verseql/generated/VerseQLParser.py
verseql/generated/VerseQLParserListener.py
verseql/generated/__init__.py
verseql-0.0.3.dist-info/LICENSE
verseql-0.0.3.dist-info/METADATA
verseql-0.0.3.dist-info/WHEEL
verseql-0.0.3.dist-info/top_level.txt
verseql-0.0.3.dist-info/RECORD
